docs/__init__.py
docs/autogen.py
skil/__init__.py
skil/base.py
skil/cli.py
skil/config.py
skil/context.py
skil/deployments.py
skil/experiments.py
skil/jobs.py
skil/models.py
skil/services.py
skil/spark.py
skil/workspaces.py
skil/resources/__init__.py
skil/resources/base.py
skil/resources/common.py
skil/resources/compute.py
skil/resources/credentials.py
skil/resources/groups.py
skil/resources/storage.py
skil/utils/__init__.py
skil/utils/io.py
skil/utils/yolo.py
skil-1.2.1.1.dist-info/DESCRIPTION.rst
skil-1.2.1.1.dist-info/METADATA
skil-1.2.1.1.dist-info/RECORD
skil-1.2.1.1.dist-info/WHEEL
skil-1.2.1.1.dist-info/entry_points.txt
skil-1.2.1.1.dist-info/metadata.json
skil-1.2.1.1.dist-info/top_level.txt
